open_data_scientist/__init__.py
open_data_scientist/cli.py
open_data_scientist/codeagent.py
open_data_scientist/utils/executors.py
open_data_scientist/utils/strings.py
open_data_scientist/utils/writer.py
open_data_scientist-0.1.0a2.dist-info/METADATA
open_data_scientist-0.1.0a2.dist-info/WHEEL
open_data_scientist-0.1.0a2.dist-info/entry_points.txt
open_data_scientist-0.1.0a2.dist-info/licenses/LICENSE
open_data_scientist-0.1.0a2.dist-info/RECORD
