Metadata-Version: 2.4
Name: open-data-scientist
Version: 0.1.0a2
Summary: ReAct Data Science Agent - AI-powered data analysis assistant
Project-URL: Homepage, https://github.com/togethercomputer/open-data-scientist
Project-URL: Repository, https://github.com/togethercomputer/open-data-scientist
Project-URL: Issues, https://github.com/togethercomputer/open-data-scientist/issues
Author: TogetherAI
License-File: LICENSE
Keywords: ai,analysis,data-science,llm,react
Classifier: Development Status :: 3 - Alpha
Classifier: Intended Audience :: Developers
Classifier: Intended Audience :: Science/Research
Classifier: License :: OSI Approved :: MIT License
Classifier: Programming Language :: Python :: 3
Classifier: Programming Language :: Python :: 3.10
Classifier: Programming Language :: Python :: 3.11
Classifier: Programming Language :: Python :: 3.12
Classifier: Topic :: Scientific/Engineering :: Artificial Intelligence
Classifier: Topic :: Scientific/Engineering :: Information Analysis
Requires-Python: >=3.10
Requires-Dist: datasets>=3.6.0
Requires-Dist: huggingface-hub>=0.32.1
Requires-Dist: ipython>=9.2.0
Requires-Dist: matplotlib>=3.7.0
Requires-Dist: numpy>=2.2.6
Requires-Dist: pandas>=2.2.3
Requires-Dist: requests>=2.31.0
Requires-Dist: rich>=14.0.0
Requires-Dist: scikit-learn>=1.3.0
Requires-Dist: scipy>=1.15.3
Requires-Dist: seaborn>=0.12.0
Requires-Dist: together>=1.0.0
Provides-Extra: dev
Requires-Dist: black>=23.0.0; extra == 'dev'
Requires-Dist: flake8>=6.0.0; extra == 'dev'
Requires-Dist: mypy>=1.0.0; extra == 'dev'
Requires-Dist: pytest>=7.0.0; extra == 'dev'
